wagtail_ckeditor/__init__.py
wagtail_ckeditor/settings.py
wagtail_ckeditor/static/wagtail_ckeditor/ckeditor.js
wagtail_ckeditor/static/wagtail_ckeditor/ckeditor.js.map
wagtail_ckeditor/static/wagtail_ckeditor/translations/af.js
wagtail_ckeditor/static/wagtail_ckeditor/translations/ar.js
wagtail_ckeditor/static/wagtail_ckeditor/translations/ast.js
wagtail_ckeditor/static/wagtail_ckeditor/translations/az.js
wagtail_ckeditor/static/wagtail_ckeditor/translations/bg.js
wagtail_ckeditor/static/wagtail_ckeditor/translations/bs.js
wagtail_ckeditor/static/wagtail_ckeditor/translations/ca.js
wagtail_ckeditor/static/wagtail_ckeditor/translations/cs.js
wagtail_ckeditor/static/wagtail_ckeditor/translations/da.js
wagtail_ckeditor/static/wagtail_ckeditor/translations/de-ch.js
wagtail_ckeditor/static/wagtail_ckeditor/translations/de.js
wagtail_ckeditor/static/wagtail_ckeditor/translations/el.js
wagtail_ckeditor/static/wagtail_ckeditor/translations/en-au.js
wagtail_ckeditor/static/wagtail_ckeditor/translations/en-gb.js
wagtail_ckeditor/static/wagtail_ckeditor/translations/en.js
wagtail_ckeditor/static/wagtail_ckeditor/translations/eo.js
wagtail_ckeditor/static/wagtail_ckeditor/translations/es.js
wagtail_ckeditor/static/wagtail_ckeditor/translations/et.js
wagtail_ckeditor/static/wagtail_ckeditor/translations/eu.js
wagtail_ckeditor/static/wagtail_ckeditor/translations/fa.js
wagtail_ckeditor/static/wagtail_ckeditor/translations/fi.js
wagtail_ckeditor/static/wagtail_ckeditor/translations/fr.js
wagtail_ckeditor/static/wagtail_ckeditor/translations/gl.js
wagtail_ckeditor/static/wagtail_ckeditor/translations/gu.js
wagtail_ckeditor/static/wagtail_ckeditor/translations/he.js
wagtail_ckeditor/static/wagtail_ckeditor/translations/hi.js
wagtail_ckeditor/static/wagtail_ckeditor/translations/hr.js
wagtail_ckeditor/static/wagtail_ckeditor/translations/hu.js
wagtail_ckeditor/static/wagtail_ckeditor/translations/id.js
wagtail_ckeditor/static/wagtail_ckeditor/translations/it.js
wagtail_ckeditor-1.2.2.dist-info/LICENSE.md
wagtail_ckeditor-1.2.2.dist-info/WHEEL
wagtail_ckeditor-1.2.2.dist-info/METADATA
wagtail_ckeditor-1.2.2.dist-info/RECORD
